MANIFEST.in
MIT-License.txt
README.md
requirements.txt
setup.cfg
setup.py
rake/SmartStoplist.txt
rake/__init__.py
rake/__init__.pyc
rake/rake.py
rake.egg-info/PKG-INFO
rake.egg-info/SOURCES.txt
rake.egg-info/dependency_links.txt
rake.egg-info/namespace_packages.txt
rake.egg-info/requires.txt
rake.egg-info/top_level.txt