Metadata-Version: 1.0
Name: rake
Version: 1.0
Summary: ('Rapid Automatic Keywords Extraction', 'Just a Practice')
Home-page: https://github.com/fishkao/rake
Author: yilan
Author-email: zhaoyinlan@live.cn
License: MIT
Keywords: Rapid automatic keywords extraction
Platform: UNKNOWN
Classifier: Programming Language :: Python
Classifier: Topic :: Software Development :: Libraries :: Python Modules
